Workbook

Sheet Read Me
B1: READ ME:
A2: 1 | B2: This spreadsheet gives you a simple Pro Forma Financial Statement Analysis
A3: 2 | B3: You are give the hisytorical data on Financial Statements from Y1-Y3 and asked for forecast for F1-F5
A4: 3 | B4: The forecast is based on the assumptions that are given in the Rate and Percentage Forecast tab.
A5: 4 | B5: Once you are done forecasting the Balance Sheet and Income Statement, you can do ratio analysis on the forecasted statements.

Sheet IncomeStatement
A1: INCOME STATEMENT
B2: Y1 | C2: Y2 | D2: Y3 | E2: F1 | F2: F2 | G2: F3 | H2: F4 | I2: F5
A3: Net Revenue
A4: Product | B4: 6171 | C4: 7067 | D4: 7063 | E4: =D4*(1+'Rate and Percentage Forecast'!E3) -> 7769.3 | F4: =E4*(1+'Rate and Percentage Forecast'!F3) -> 8546.23 | G4: =F4*(1+'Rate and Percentage Forecast'!G3) -> 9400.853 | H4: =G4*(1+'Rate and Percentage Forecast'!H3) -> 10340.938 | I4: =H4*(1+'Rate and Percentage Forecast'!I3) -> 11375.032
A5: Service | B5: 3344 | C5: 3401 | D5: 3503 | E5: =D5*(1+'Rate and Percentage Forecast'!E4) -> 3853.3 | F5: =E5*(1+'Rate and Percentage Forecast'!F4) -> 4238.63 | G5: =F5*(1+'Rate and Percentage Forecast'!G4) -> 4662.493 | H5: =G5*(1+'Rate and Percentage Forecast'!H4) -> 5128.7423 | I5: =H5*(1+'Rate and Percentage Forecast'!I4) -> 5641.6165
A6: Financing income | B6: 31 | C6: 35 | D6: 37 | E6: =D6*(1+'Rate and Percentage Forecast'!E5) -> 40.7 | F6: =E6*(1+'Rate and Percentage Forecast'!F5) -> 44.77 | G6: =F6*(1+'Rate and Percentage Forecast'!G5) -> 49.247 | H6: =G6*(1+'Rate and Percentage Forecast'!H5) -> 54.1717 | I6: =H6*(1+'Rate and Percentage Forecast'!I5) -> 59.58887
A7: Total Net Revenue | B7: =SUM(B4:B6) -> 9546 | C7: =SUM(C4:C6) -> 10503 | D7: =SUM(D4:D6) -> 10603 | E7: =SUM(E4:E6) -> 11663.3 | F7: =SUM(F4:F6) -> 12829.63 | G7: =SUM(G4:G6) -> 14112.593 | H7: =SUM(H4:H6) -> 15523.852 | I7: =SUM(I4:I6) -> 17076.238
A9: Cost and Expenses
A10: Cost of product | B10: 4709 | C10: 5422 | D10: 5431 | E10: =E4*'Rate and Percentage Forecast'!E11 -> 5974.1 | F10: =F4*'Rate and Percentage Forecast'!F11 -> 6571.51 | G10: =G4*'Rate and Percentage Forecast'!G11 -> 7228.661 | H10: =H4*'Rate and Percentage Forecast'!H11 -> 7951.5271 | I10: =I4*'Rate and Percentage Forecast'!I11 -> 8746.6798
A11: Cost of service | B11: 2555 | C11: 2549 | D11: 2671 | E11: =E5*'Rate and Percentage Forecast'!E12 -> 2938.1 | F11: =F5*'Rate and Percentage Forecast'!F12 -> 3231.91 | G11: =G5*'Rate and Percentage Forecast'!G12 -> 3555.101 | H11: =H5*'Rate and Percentage Forecast'!H12 -> 3910.6111 | I11: =I5*'Rate and Percentage Forecast'!I12 -> 4301.6722
A12: Financing interest | B12: 27 | C12: 25 | D12: 26 | E12: =E6*'Rate and Percentage Forecast'!E13 -> 28.6 | F12: =F6*'Rate and Percentage Forecast'!F13 -> 31.46 | G12: =G6*'Rate and Percentage Forecast'!G13 -> 34.606 | H12: =H6*'Rate and Percentage Forecast'!H13 -> 38.0666 | I12: =I6*'Rate and Percentage Forecast'!I13 -> 41.87326
A13: Research and development | B13: 235 | C13: 247 | D13: 271 | E13: =E7*'Rate and Percentage Forecast'!E14 -> 298.1 | F13: =F7*'Rate and Percentage Forecast'!F14 -> 327.91 | G13: =G7*'Rate and Percentage Forecast'!G14 -> 360.701 | H13: =H7*'Rate and Percentage Forecast'!H14 -> 396.7711 | I13: =I7*'Rate and Percentage Forecast'!I14 -> 436.44821
A14: Selling, general, and administrative | B14: 971 | C14: 1060 | D14: 1122 | E14: =E7*'Rate and Percentage Forecast'!E15 -> 1234.2 | F14: =F7*'Rate and Percentage Forecast'!F15 -> 1357.62 | G14: =G7*'Rate and Percentage Forecast'!G15 -> 1493.382 | H14: =H7*'Rate and Percentage Forecast'!H15 -> 1642.7202 | I14: =I7*'Rate and Percentage Forecast'!I15 -> 1806.9922
A15: Other expenses | B15: 205 | C15: 243 | D15: 277 | E15: =E7*'Rate and Percentage Forecast'!E16 -> 304.7 | F15: =F7*'Rate and Percentage Forecast'!F16 -> 335.17 | G15: =G7*'Rate and Percentage Forecast'!G16 -> 368.687 | H15: =H7*'Rate and Percentage Forecast'!H16 -> 405.5557 | I15: =I7*'Rate and Percentage Forecast'!I16 -> 446.11127
A16: Total Operating Expenses | B16: =SUM(B10:B15) -> 8702 | C16: =SUM(C10:C15) -> 9546 | D16: =SUM(D10:D15) -> 9798 | E16: =SUM(E10:E15) -> 10777.8 | F16: =SUM(F10:F15) -> 11855.58 | G16: =SUM(G10:G15) -> 13041.138 | H16: =SUM(H10:H15) -> 14345.252 | I16: =SUM(I10:I15) -> 15779.777
A18: EBIT | B18: =B7-B16 -> 844 | C18: =C7-C16 -> 957 | D18: =D7-D16 -> 805 | E18: =E7-E16 -> 885.5 | F18: =F7-F16 -> 974.05 | G18: =G7-G16 -> 1071.455 | H18: =H7-H16 -> 1178.6005 | I18: =I7-I16 -> 1296.4606
A19: Interst and other, net | B19: 60 | C19: 42 | D19: 58 | E19: ='Rate and Percentage Forecast'!E6*(BalanceSheet!E18+BalanceSheet!E27) -> 61.801392 | F19: ='Rate and Percentage Forecast'!F6*(BalanceSheet!F18+BalanceSheet!F27) -> 65.946532 | G19: ='Rate and Percentage Forecast'!G6*(BalanceSheet!G18+BalanceSheet!G27) -> 70.469132 | H19: ='Rate and Percentage Forecast'!H6*(BalanceSheet!H18+BalanceSheet!H27) -> 75.406264 | I19: ='Rate and Percentage Forecast'!I6*(BalanceSheet!I18+BalanceSheet!I27) -> 80.798693
A20: EBT | B20: =B18-B19 -> 784 | C20: =C18-C19 -> 915 | D20: =D18-D19 -> 747 | E20: =E18-E19 -> 823.69861 | F20: =F18-F19 -> 908.10347 | G20: =G18-G19 -> 1000.9859 | H20: =H18-H19 -> 1103.1942 | I20: =I18-I19 -> 1215.6619
A21: Provision for taxes | B21: 146 | C21: 184 | D21: 159 | E21: =E20*'Rate and Percentage Forecast'!E7 -> 175.32541 | F21: =F20*'Rate and Percentage Forecast'!F7 -> 193.2911 | G21: =G20*'Rate and Percentage Forecast'!G7 -> 213.06125 | H21: =H20*'Rate and Percentage Forecast'!H7 -> 234.81644 | I21: =I20*'Rate and Percentage Forecast'!I7 -> 258.75534
A22: Net Income | B22: =B20-B21 -> 638 | C22: =C20-C21 -> 731 | D22: =D20-D21 -> 588 | E22: =E20-E21 -> 648.3732 | F22: =F20-F21 -> 714.81237 | G22: =G20-G21 -> 787.92462 | H22: =H20-H21 -> 868.37779 | I22: =I20-I21 -> 956.90652

Sheet BalanceSheet
A1: BALANCE SHEET
B2: Y1 | C2: Y2 | D2: Y3 | E2: F1 | F2: F2 | G2: F3 | H2: F4 | I2: F5
A3: Current Assets
A4: Cash and cash equivalent | B4: 1107 | C4: 911 | D4: 670 | E4: =IncomeStatement!E7*'Rate and Percentage Forecast'!E20 -> 737 | F4: =IncomeStatement!F7*'Rate and Percentage Forecast'!F20 -> 810.7 | G4: =IncomeStatement!G7*'Rate and Percentage Forecast'!G20 -> 891.77 | H4: =IncomeStatement!H7*'Rate and Percentage Forecast'!H20 -> 980.947 | I4: =IncomeStatement!I7*'Rate and Percentage Forecast'!I20 -> 1079.0417
A5: Account receivables | B5: 1378 | C5: 1540 | D5: 1519 | E5: =IncomeStatement!E7*'Rate and Percentage Forecast'!E21 -> 1670.9 | F5: =IncomeStatement!F7*'Rate and Percentage Forecast'!F21 -> 1837.99 | G5: =IncomeStatement!G7*'Rate and Percentage Forecast'!G21 -> 2021.789 | H5: =IncomeStatement!H7*'Rate and Percentage Forecast'!H21 -> 2223.9679 | I5: =IncomeStatement!I7*'Rate and Percentage Forecast'!I21 -> 2446.3647
A6: Financing receivables | B6: 223 | C6: 249 | D6: 264 | E6: =IncomeStatement!E7*'Rate and Percentage Forecast'!E22 -> 290.4 | F6: =IncomeStatement!F7*'Rate and Percentage Forecast'!F22 -> 319.44 | G6: =IncomeStatement!G7*'Rate and Percentage Forecast'!G22 -> 351.384 | H6: =IncomeStatement!H7*'Rate and Percentage Forecast'!H22 -> 386.5224 | I6: =IncomeStatement!I7*'Rate and Percentage Forecast'!I22 -> 425.17464
A7: Inventory | B7: 511 | C7: 539 | D7: 624 | E7: =IncomeStatement!E7*'Rate and Percentage Forecast'!E23 -> 686.4 | F7: =IncomeStatement!F7*'Rate and Percentage Forecast'!F23 -> 755.04 | G7: =IncomeStatement!G7*'Rate and Percentage Forecast'!G23 -> 830.544 | H7: =IncomeStatement!H7*'Rate and Percentage Forecast'!H23 -> 913.5984 | I7: =IncomeStatement!I7*'Rate and Percentage Forecast'!I23 -> 1004.9582
A8: Other current assets | B8: 1160 | C8: 1277 | D8: 1175 | E8: =IncomeStatement!E7*'Rate and Percentage Forecast'!E24 -> 1292.5 | F8: =IncomeStatement!F7*'Rate and Percentage Forecast'!F24 -> 1421.75 | G8: =IncomeStatement!G7*'Rate and Percentage Forecast'!G24 -> 1563.925 | H8: =IncomeStatement!H7*'Rate and Percentage Forecast'!H24 -> 1720.3175 | I8: =IncomeStatement!I7*'Rate and Percentage Forecast'!I24 -> 1892.3493
A9: Total Current Assets | B9: =SUM(B4:B8) -> 4379 | C9: =SUM(C4:C8) -> 4516 | D9: =SUM(D4:D8) -> 4252 | E9: =SUM(E4:E8) -> 4677.2 | F9: =SUM(F4:F8) -> 5144.92 | G9: =SUM(G4:G8) -> 5659.412 | H9: =SUM(H4:H8) -> 6225.3532 | I9: =SUM(I4:I8) -> 6847.8885
A11: Property, plant, and equipment | B11: 939 | C11: 980 | D11: 1024 | E11: =IncomeStatement!E7*'Rate and Percentage Forecast'!E25 -> 1126.4 | F11: =IncomeStatement!F7*'Rate and Percentage Forecast'!F25 -> 1239.04 | G11: =IncomeStatement!G7*'Rate and Percentage Forecast'!G25 -> 1362.944 | H11: =IncomeStatement!H7*'Rate and Percentage Forecast'!H25 -> 1499.2384 | I11: =IncomeStatement!I7*'Rate and Percentage Forecast'!I25 -> 1649.1622
A12: Long-term financing receivables and other assets | B12: 941 | C12: 1019 | D12: 896 | E12: =IncomeStatement!E7*'Rate and Percentage Forecast'!E26 -> 985.6 | F12: =IncomeStatement!F7*'Rate and Percentage Forecast'!F26 -> 1084.16 | G12: =IncomeStatement!G7*'Rate and Percentage Forecast'!G26 -> 1192.576 | H12: =IncomeStatement!H7*'Rate and Percentage Forecast'!H26 -> 1311.8336 | I12: =IncomeStatement!I7*'Rate and Percentage Forecast'!I26 -> 1443.017
A13: Other long-term assets | B13: 4197 | C13: 5477 | D13: 6975 | E13: =IncomeStatement!E7*'Rate and Percentage Forecast'!E27 -> 7672.5 | F13: =IncomeStatement!F7*'Rate and Percentage Forecast'!F27 -> 8439.75 | G13: =IncomeStatement!G7*'Rate and Percentage Forecast'!G27 -> 9283.725 | H13: =IncomeStatement!H7*'Rate and Percentage Forecast'!H27 -> 10212.098 | I13: =IncomeStatement!I7*'Rate and Percentage Forecast'!I27 -> 11233.307
A15: Total Assets | B15: =SUM(B9:B13) -> 10456 | C15: =SUM(C9:C13) -> 11992 | D15: =SUM(D9:D13) -> 13147 | E15: =SUM(E9:E13) -> 14461.7 | F15: =SUM(F9:F13) -> 15907.87 | G15: =SUM(G9:G13) -> 17498.657 | H15: =SUM(H9:H13) -> 19248.523 | I15: =SUM(I9:I13) -> 21173.375
A17: Current Liabilities
A18: Notes payable and short-term borrowing | B18: 154 | C18: 587 | D18: 674 | E18: =IncomeStatement!E7*'Rate and Percentage Forecast'!E30 -> 741.4 | F18: =IncomeStatement!F7*'Rate and Percentage Forecast'!F30 -> 815.54 | G18: =IncomeStatement!G7*'Rate and Percentage Forecast'!G30 -> 897.094 | H18: =IncomeStatement!H7*'Rate and Percentage Forecast'!H30 -> 986.8034 | I18: =IncomeStatement!I7*'Rate and Percentage Forecast'!I30 -> 1085.4837
A19: Account payable | B19: 1234 | C19: 1197 | D19: 1229 | E19: =IncomeStatement!E7*'Rate and Percentage Forecast'!E31 -> 1351.9 | F19: =IncomeStatement!F7*'Rate and Percentage Forecast'!F31 -> 1487.09 | G19: =IncomeStatement!G7*'Rate and Percentage Forecast'!G31 -> 1635.799 | H19: =IncomeStatement!H7*'Rate and Percentage Forecast'!H31 -> 1799.3789 | I19: =IncomeStatement!I7*'Rate and Percentage Forecast'!I31 -> 1979.3168
A20: Employee compensation and benefits | B20: 339 | C20: 355 | D20: 333 | E20: =IncomeStatement!E7*'Rate and Percentage Forecast'!E32 -> 366.3 | F20: =IncomeStatement!F7*'Rate and Percentage Forecast'!F32 -> 402.93 | G20: =IncomeStatement!G7*'Rate and Percentage Forecast'!G32 -> 443.223 | H20: =IncomeStatement!H7*'Rate and Percentage Forecast'!H32 -> 487.5453 | I20: =IncomeStatement!I7*'Rate and Percentage Forecast'!I32 -> 536.29983
A21: Taxes on earnings | B21: 76 | C21: 67 | D21: 87 | E21: =IncomeStatement!E7*'Rate and Percentage Forecast'!E37 -> 95.7 | F21: =IncomeStatement!F7*'Rate and Percentage Forecast'!F37 -> 105.27 | G21: =IncomeStatement!G7*'Rate and Percentage Forecast'!G37 -> 115.797 | H21: =IncomeStatement!H7*'Rate and Percentage Forecast'!H37 -> 127.3767 | I21: =IncomeStatement!I7*'Rate and Percentage Forecast'!I37 -> 140.11437
A22: Deferred revenues | B22: 515 | C22: 561 | D22: 621 | E22: =IncomeStatement!E7*'Rate and Percentage Forecast'!E33 -> 683.1 | F22: =IncomeStatement!F7*'Rate and Percentage Forecast'!F33 -> 751.41 | G22: =IncomeStatement!G7*'Rate and Percentage Forecast'!G33 -> 826.551 | H22: =IncomeStatement!H7*'Rate and Percentage Forecast'!H33 -> 909.2061 | I22: =IncomeStatement!I7*'Rate and Percentage Forecast'!I33 -> 1000.1267
A23: Accrued restructuring | B23: 92 | C23: 76 | D23: 55 | E23: =IncomeStatement!E7*'Rate and Percentage Forecast'!E34 -> 60.5 | F23: =IncomeStatement!F7*'Rate and Percentage Forecast'!F34 -> 66.55 | G23: =IncomeStatement!G7*'Rate and Percentage Forecast'!G34 -> 73.205 | H23: =IncomeStatement!H7*'Rate and Percentage Forecast'!H34 -> 80.5255 | I23: =IncomeStatement!I7*'Rate and Percentage Forecast'!I34 -> 88.57805
A24: Other accrued liabilities | B24: 1173 | C24: 1275 | D24: 1205 | E24: =IncomeStatement!E7*'Rate and Percentage Forecast'!E35 -> 1325.5 | F24: =IncomeStatement!F7*'Rate and Percentage Forecast'!F35 -> 1458.05 | G24: =IncomeStatement!G7*'Rate and Percentage Forecast'!G35 -> 1603.855 | H24: =IncomeStatement!H7*'Rate and Percentage Forecast'!H35 -> 1764.2405 | I24: =IncomeStatement!I7*'Rate and Percentage Forecast'!I35 -> 1940.6646
A25: Total Current Liabilities | B25: =SUM(B18:B24) -> 3583 | C25: =SUM(C18:C24) -> 4118 | D25: =SUM(D18:D24) -> 4204 | E25: =SUM(E18:E24) -> 4624.4 | F25: =SUM(F18:F24) -> 5086.84 | G25: =SUM(G18:G24) -> 5595.524 | H25: =SUM(H18:H24) -> 6155.0764 | I25: =SUM(I18:I24) -> 6770.584
A27: Long-term debt | B27: 1165 | C27: 1272 | D27: 1879 | E27: =E32-E25-E28-E30 -> 1978.9268 | F27: =F32-F25-F28-F30 -> 2087.2444 | G27: =G32-G25-G28-G30 -> 2204.7628 | H27: =H32-H25-H28-H30 -> 2332.3723 | I27: =I32-I25-I28-I30 -> 2471.0518
A28: Other liablities | B28: 1421 | C28: 1588 | D28: 1460 | E28: =IncomeStatement!E7*'Rate and Percentage Forecast'!E36 -> 1606 | F28: =IncomeStatement!F7*'Rate and Percentage Forecast'!F36 -> 1766.6 | G28: =IncomeStatement!G7*'Rate and Percentage Forecast'!G36 -> 1943.26 | H28: =IncomeStatement!H7*'Rate and Percentage Forecast'!H36 -> 2137.586 | I28: =IncomeStatement!I7*'Rate and Percentage Forecast'!I36 -> 2351.3446
A30: Shareholders' Equity | B30: 4285 | C30: 5015 | D30: 5604 | E30: =D30+IncomeStatement!E22 -> 6252.3732 | F30: =E30+IncomeStatement!F22 -> 6967.1856 | G30: =F30+IncomeStatement!G22 -> 7755.1102 | H30: =G30+IncomeStatement!H22 -> 8623.488 | I30: =H30+IncomeStatement!I22 -> 9580.3945
A32: Total Liabilities and Shareholders' Equity | B32: =SUM(B25:B30) -> 10454 | C32: =SUM(C25:C30) -> 11993 | D32: =SUM(D25:D30) -> 13147 | E32: =E15 -> 14461.7 | F32: =F15 -> 15907.87 | G32: =G15 -> 17498.657 | H32: =H15 -> 19248.523 | I32: =I15 -> 21173.375

Sheet Rate and Percentage Forecast
B1: Y1 | C1: Y2 | D1: Y3 | E1: F1 | F1: F2 | G1: F3 | H1: F4 | I1: F5
A2: Rates Assumptions
A3: Product revenue growth rate | E3: 0.1 | F3: 0.1 | G3: 0.1 | H3: 0.1 | I3: 0.1
A4: Service revenue growth rate | E4: 0.1 | F4: 0.1 | G4: 0.1 | H4: 0.1 | I4: 0.1
A5: Financing income revenue growth rate | E5: 0.1 | F5: 0.1 | G5: 0.1 | H5: 0.1 | I5: 0.1
A6: Interest on borrowing (average) | B6: =IncomeStatement!B19/(BalanceSheet!B18+BalanceSheet!B27) -> 0.045489007 | C6: =IncomeStatement!C19/(BalanceSheet!C18+BalanceSheet!C27) -> 0.022592792 | D6: =IncomeStatement!D19/(BalanceSheet!D18+BalanceSheet!D27) -> 0.022718371 | E6: =D6 -> 0.022718371 | F6: =E6 -> 0.022718371 | G6: =F6 -> 0.022718371 | H6: =G6 -> 0.022718371 | I6: =H6 -> 0.022718371
A7: Tax rate | B7: =IncomeStatement!B21/IncomeStatement!B20 -> 0.18622449 | C7: =IncomeStatement!C21/IncomeStatement!C20 -> 0.2010929 | D7: =IncomeStatement!D21/IncomeStatement!D20 -> 0.21285141 | E7: =D7 -> 0.21285141 | F7: =E7 -> 0.21285141 | G7: =F7 -> 0.21285141 | H7: =G7 -> 0.21285141 | I7: =H7 -> 0.21285141
A9: Percentage Assumptions
A10: Cost percentages
A11: Cost of product/Net revenue from product | B11: =IncomeStatement!B10/IncomeStatement!B4 -> 0.7630854 | C11: =IncomeStatement!C10/IncomeStatement!C4 -> 0.76722796 | D11: =IncomeStatement!D10/IncomeStatement!D4 -> 0.76893671 | E11: =D11 -> 0.76893671 | F11: =E11 -> 0.76893671 | G11: =F11 -> 0.76893671 | H11: =G11 -> 0.76893671 | I11: =H11 -> 0.76893671
A12: Cost of service/Net revenue from service | B12: =IncomeStatement!B11/IncomeStatement!B5 -> 0.76405502 | C12: =IncomeStatement!C11/IncomeStatement!C5 -> 0.74948545 | D12: =IncomeStatement!D11/IncomeStatement!D5 -> 0.76248929 | E12: =D12 -> 0.76248929 | F12: =E12 -> 0.76248929 | G12: =F12 -> 0.76248929 | H12: =G12 -> 0.76248929 | I12: =H12 -> 0.76248929
A13: Financing interest/Financing income | B13: =IncomeStatement!B12/IncomeStatement!B6 -> 0.87096774 | C13: =IncomeStatement!C12/IncomeStatement!C6 -> 0.71428571 | D13: =IncomeStatement!D12/IncomeStatement!D6 -> 0.7027027 | E13: =D13 -> 0.7027027 | F13: =E13 -> 0.7027027 | G13: =F13 -> 0.7027027 | H13: =G13 -> 0.7027027 | I13: =H13 -> 0.7027027
A14: R&D/Total revenue | B14: =IncomeStatement!B13/IncomeStatement!B7 -> 0.024617641 | C14: =IncomeStatement!C13/IncomeStatement!C7 -> 0.02351709 | D14: =IncomeStatement!D13/IncomeStatement!D7 -> 0.025558804 | E14: =D14 -> 0.025558804 | F14: =E14 -> 0.025558804 | G14: =F14 -> 0.025558804 | H14: =G14 -> 0.025558804 | I14: =H14 -> 0.025558804
A15: SGA/Total revenue | B15: =IncomeStatement!B14/IncomeStatement!B7 -> 0.101718 | C15: =IncomeStatement!C14/IncomeStatement!C7 -> 0.10092355 | D15: =IncomeStatement!D14/IncomeStatement!D7 -> 0.10581911 | E15: =D15 -> 0.10581911 | F15: =E15 -> 0.10581911 | G15: =F15 -> 0.10581911 | H15: =G15 -> 0.10581911 | I15: =H15 -> 0.10581911
A16: Other expenses/Total revenue | B16: =IncomeStatement!B15/IncomeStatement!B7 -> 0.021474963 | C16: =IncomeStatement!C15/IncomeStatement!C7 -> 0.023136247 | D16: =IncomeStatement!D15/IncomeStatement!D7 -> 0.026124682 | E16: =D16 -> 0.026124682 | F16: =E16 -> 0.026124682 | G16: =F16 -> 0.026124682 | H16: =G16 -> 0.026124682 | I16: =H16 -> 0.026124682
A17: Total operating expenses/Total revenue | B17: =IncomeStatement!B16/IncomeStatement!B7 -> 0.911586 | C17: =IncomeStatement!C16/IncomeStatement!C7 -> 0.90888318 | D17: =IncomeStatement!D16/IncomeStatement!D7 -> 0.92407809 | E17: =D17 -> 0.92407809 | F17: =E17 -> 0.92407809 | G17: =F17 -> 0.92407809 | H17: =G17 -> 0.92407809 | I17: =H17 -> 0.92407809
A19: Asset percentages
A20: Cash/Total revenue | B20: =BalanceSheet!B4/IncomeStatement!B7 -> 0.1159648 | C20: =BalanceSheet!C4/IncomeStatement!C7 -> 0.086737123 | D20: =BalanceSheet!D4/IncomeStatement!D7 -> 0.063189663 | E20: =D20 -> 0.063189663 | F20: =E20 -> 0.063189663 | G20: =F20 -> 0.063189663 | H20: =G20 -> 0.063189663 | I20: =H20 -> 0.063189663
A21: Account receivables/Total revenue | B21: =BalanceSheet!B5/IncomeStatement!B7 -> 0.14435366 | C21: =BalanceSheet!C5/IncomeStatement!C7 -> 0.14662477 | D21: =BalanceSheet!D5/IncomeStatement!D7 -> 0.14326134 | E21: =D21 -> 0.14326134 | F21: =E21 -> 0.14326134 | G21: =F21 -> 0.14326134 | H21: =G21 -> 0.14326134 | I21: =H21 -> 0.14326134
A22: Financing receivable/Total revenue | B22: =BalanceSheet!B6/IncomeStatement!B7 -> 0.02336057 | C22: =BalanceSheet!C6/IncomeStatement!C7 -> 0.023707512 | D22: =BalanceSheet!D6/IncomeStatement!D7 -> 0.024898614 | E22: =D22 -> 0.024898614 | F22: =E22 -> 0.024898614 | G22: =F22 -> 0.024898614 | H22: =G22 -> 0.024898614 | I22: =H22 -> 0.024898614
A23: Inventory/Total revenue | B23: =BalanceSheet!B7/IncomeStatement!B7 -> 0.053530274 | C23: =BalanceSheet!C7/IncomeStatement!C7 -> 0.051318671 | D23: =BalanceSheet!D7/IncomeStatement!D7 -> 0.058851269 | E23: =D23 -> 0.058851269 | F23: =E23 -> 0.058851269 | G23: =F23 -> 0.058851269 | H23: =G23 -> 0.058851269 | I23: =H23 -> 0.058851269
A24: Other current assets/Total revenue | B24: =BalanceSheet!B8/IncomeStatement!B7 -> 0.12151687 | C24: =BalanceSheet!C8/IncomeStatement!C7 -> 0.12158431 | D24: =BalanceSheet!D8/IncomeStatement!D7 -> 0.11081769 | E24: =D24 -> 0.11081769 | F24: =E24 -> 0.11081769 | G24: =F24 -> 0.11081769 | H24: =G24 -> 0.11081769 | I24: =H24 -> 0.11081769
A25: Property, plant, and equipment/Total revenue | B25: =BalanceSheet!B11/IncomeStatement!B7 -> 0.098365808 | C25: =BalanceSheet!C11/IncomeStatement!C7 -> 0.093306674 | D25: =BalanceSheet!D11/IncomeStatement!D7 -> 0.096576441 | E25: =D25 -> 0.096576441 | F25: =E25 -> 0.096576441 | G25: =F25 -> 0.096576441 | H25: =G25 -> 0.096576441 | I25: =H25 -> 0.096576441
A26: Long-term financing receivables/Total revenue | B26: =BalanceSheet!B12/IncomeStatement!B7 -> 0.09857532 | C26: =BalanceSheet!C12/IncomeStatement!C7 -> 0.097019899 | D26: =BalanceSheet!D12/IncomeStatement!D7 -> 0.084504386 | E26: =D26 -> 0.084504386 | F26: =E26 -> 0.084504386 | G26: =F26 -> 0.084504386 | H26: =G26 -> 0.084504386 | I26: =H26 -> 0.084504386
A27: Other long-term assets/Total revenue | B27: =BalanceSheet!B13/IncomeStatement!B7 -> 0.43966059 | C27: =BalanceSheet!C13/IncomeStatement!C7 -> 0.52147006 | D27: =BalanceSheet!D13/IncomeStatement!D7 -> 0.65783269 | E27: =D27 -> 0.65783269 | F27: =E27 -> 0.65783269 | G27: =F27 -> 0.65783269 | H27: =G27 -> 0.65783269 | I27: =H27 -> 0.65783269
A29: Liabilities percentages
A30: Short-term borrowing/Total revenue | B30: =BalanceSheet!B18/IncomeStatement!B7 -> 0.016132411 | C30: =BalanceSheet!C18/IncomeStatement!C7 -> 0.055888794 | D30: =BalanceSheet!D18/IncomeStatement!D7 -> 0.063566915 | E30: =D30 -> 0.063566915 | F30: =E30 -> 0.063566915 | G30: =F30 -> 0.063566915 | H30: =G30 -> 0.063566915 | I30: =H30 -> 0.063566915
A31: Account payable/Total revenue | B31: =BalanceSheet!B19/IncomeStatement!B7 -> 0.1292688 | C31: =BalanceSheet!C19/IncomeStatement!C7 -> 0.11396744 | D31: =BalanceSheet!D19/IncomeStatement!D7 -> 0.11591059 | E31: =D31 -> 0.11591059 | F31: =E31 -> 0.11591059 | G31: =F31 -> 0.11591059 | H31: =G31 -> 0.11591059 | I31: =H31 -> 0.11591059
A32: Employee compensation/Total revenue | B32: =BalanceSheet!B20/IncomeStatement!B7 -> 0.035512256 | C32: =BalanceSheet!C20/IncomeStatement!C7 -> 0.033799867 | D32: =BalanceSheet!D20/IncomeStatement!D7 -> 0.031406206 | E32: =D32 -> 0.031406206 | F32: =E32 -> 0.031406206 | G32: =F32 -> 0.031406206 | H32: =G32 -> 0.031406206 | I32: =H32 -> 0.031406206
A33: Deferred revenue/Total revenue | B33: =BalanceSheet!B22/IncomeStatement!B7 -> 0.053949298 | C33: =BalanceSheet!C22/IncomeStatement!C7 -> 0.05341331 | D33: =BalanceSheet!D22/IncomeStatement!D7 -> 0.05856833 | E33: =D33 -> 0.05856833 | F33: =E33 -> 0.05856833 | G33: =F33 -> 0.05856833 | H33: =G33 -> 0.05856833 | I33: =H33 -> 0.05856833
A34: Accrued restructurng/Total revenue | B34: =BalanceSheet!B23/IncomeStatement!B7 -> 0.0096375445 | C34: =BalanceSheet!C23/IncomeStatement!C7 -> 0.0072360278 | D34: =BalanceSheet!D23/IncomeStatement!D7 -> 0.0051872112 | E34: =D34 -> 0.0051872112 | F34: =E34 -> 0.0051872112 | G34: =F34 -> 0.0051872112 | H34: =G34 -> 0.0051872112 | I34: =H34 -> 0.0051872112
A35: Other accrued liabilities/Total revenue | B35: =BalanceSheet!B24/IncomeStatement!B7 -> 0.12287869 | C35: =BalanceSheet!C24/IncomeStatement!C7 -> 0.12139389 | D35: =BalanceSheet!D24/IncomeStatement!D7 -> 0.11364708 | E35: =D35 -> 0.11364708 | F35: =E35 -> 0.11364708 | G35: =F35 -> 0.11364708 | H35: =G35 -> 0.11364708 | I35: =H35 -> 0.11364708
A36: Other liabilities/Total revenue | B36: =BalanceSheet!B28/IncomeStatement!B7 -> 0.14885816 | C36: =BalanceSheet!C28/IncomeStatement!C7 -> 0.1511949 | D36: =BalanceSheet!D28/IncomeStatement!D7 -> 0.13769688 | E36: =D36 -> 0.13769688 | F36: =E36 -> 0.13769688 | G36: =F36 -> 0.13769688 | H36: =G36 -> 0.13769688 | I36: =H36 -> 0.13769688
A37: Taxes on earnings/Total revenue | B37: =BalanceSheet!B21/IncomeStatement!B7 -> 0.0079614498 | C37: =BalanceSheet!C21/IncomeStatement!C7 -> 0.0063791298 | D37: =BalanceSheet!D21/IncomeStatement!D7 -> 0.0082052249 | E37: =D37 -> 0.0082052249 | F37: =E37 -> 0.0082052249 | G37: =F37 -> 0.0082052249 | H37: =G37 -> 0.0082052249 | I37: =H37 -> 0.0082052249

Sheet Ratio Analysis
B1: Y1 | C1: Y2 | D1: Y3 | E1: F1 | F1: F2 | G1: F3 | H1: F4 | I1: F5
A2: Performace Ratios:
A3: ROA | B3: =IncomeStatement!B22/BalanceSheet!B15 -> 0.061017598 | C3: =IncomeStatement!C22/BalanceSheet!C15 -> 0.060957305 | D3: =IncomeStatement!D22/BalanceSheet!D15 -> 0.044725032 | E3: =IncomeStatement!E22/BalanceSheet!E15 -> 0.044833816 | F3: =IncomeStatement!F22/BalanceSheet!F15 -> 0.044934512 | G3: =IncomeStatement!G22/BalanceSheet!G15 -> 0.045027719 | H3: =IncomeStatement!H22/BalanceSheet!H15 -> 0.045113997 | I3: =IncomeStatement!I22/BalanceSheet!I15 -> 0.045193859
A4: ROE | B4: =IncomeStatement!B22/BalanceSheet!B30 -> 0.14889148 | C4: =IncomeStatement!C22/BalanceSheet!C30 -> 0.14576271 | D4: =IncomeStatement!D22/BalanceSheet!D30 -> 0.10492505 | E4: =IncomeStatement!E22/BalanceSheet!E30 -> 0.10370034 | F4: =IncomeStatement!F22/BalanceSheet!F30 -> 0.102597 | G4: =IncomeStatement!G22/BalanceSheet!G30 -> 0.1016007 | H4: =IncomeStatement!H22/BalanceSheet!H30 -> 0.10069914 | I4: =IncomeStatement!I22/BalanceSheet!I30 -> 0.099881745
A5: Operating Profit | B5: =IncomeStatement!B18/IncomeStatement!B7 -> 0.088413995 | C5: =IncomeStatement!C18/IncomeStatement!C7 -> 0.091116824 | D5: =IncomeStatement!D18/IncomeStatement!D7 -> 0.075921909 | E5: =IncomeStatement!E18/IncomeStatement!E7 -> 0.075921909 | F5: =IncomeStatement!F18/IncomeStatement!F7 -> 0.075921909 | G5: =IncomeStatement!G18/IncomeStatement!G7 -> 0.075921909 | H5: =IncomeStatement!H18/IncomeStatement!H7 -> 0.075921909 | I5: =IncomeStatement!I18/IncomeStatement!I7 -> 0.075921909
A6: Net Profit | B6: =IncomeStatement!B22/IncomeStatement!B7 -> 0.066834276 | C6: =IncomeStatement!C22/IncomeStatement!C7 -> 0.069599162 | D6: =IncomeStatement!D22/IncomeStatement!D7 -> 0.055456003 | E6: =IncomeStatement!E22/IncomeStatement!E7 -> 0.055590888 | F6: =IncomeStatement!F22/IncomeStatement!F7 -> 0.055715743 | G6: =IncomeStatement!G22/IncomeStatement!G7 -> 0.055831315 | H6: =IncomeStatement!H22/IncomeStatement!H7 -> 0.055938293 | I6: =IncomeStatement!I22/IncomeStatement!I7 -> 0.056037316
A7: Leverage & Liquidity Ratios:
A8: Current Ratio | B8: =BalanceSheet!B9/BalanceSheet!B25 -> 1.2221602 | C8: =BalanceSheet!C9/BalanceSheet!C25 -> 1.0966489 | D8: =BalanceSheet!D9/BalanceSheet!D25 -> 1.0114177 | E8: =BalanceSheet!E9/BalanceSheet!E25 -> 1.0114177 | F8: =BalanceSheet!F9/BalanceSheet!F25 -> 1.0114177 | G8: =BalanceSheet!G9/BalanceSheet!G25 -> 1.0114177 | H8: =BalanceSheet!H9/BalanceSheet!H25 -> 1.0114177 | I8: =BalanceSheet!I9/BalanceSheet!I25 -> 1.0114177
A9: Quick Ratio | B9: =(BalanceSheet!B9-BalanceSheet!B7)/BalanceSheet!B25 -> 1.0795423 | C9: =(BalanceSheet!C9-BalanceSheet!C7)/BalanceSheet!C25 -> 0.96576008 | D9: =(BalanceSheet!D9-BalanceSheet!D7)/BalanceSheet!D25 -> 0.86298763 | E9: =(BalanceSheet!E9-BalanceSheet!E7)/BalanceSheet!E25 -> 0.86298763 | F9: =(BalanceSheet!F9-BalanceSheet!F7)/BalanceSheet!F25 -> 0.86298763 | G9: =(BalanceSheet!G9-BalanceSheet!G7)/BalanceSheet!G25 -> 0.86298763 | H9: =(BalanceSheet!H9-BalanceSheet!H7)/BalanceSheet!H25 -> 0.86298763 | I9: =(BalanceSheet!I9-BalanceSheet!I7)/BalanceSheet!I25 -> 0.86298763
A10: Debt/Equity | B10: =(BalanceSheet!B18+BalanceSheet!B27)/BalanceSheet!B30 -> 0.30781797 | C10: =(BalanceSheet!C18+BalanceSheet!C27)/BalanceSheet!C30 -> 0.37068794 | D10: =(BalanceSheet!D18+BalanceSheet!D27)/BalanceSheet!D30 -> 0.45556745 | E10: =(BalanceSheet!E18+BalanceSheet!E27)/BalanceSheet!E30 -> 0.43508708 | F10: =(BalanceSheet!F18+BalanceSheet!F27)/BalanceSheet!F30 -> 0.41663659 | G10: =(BalanceSheet!G18+BalanceSheet!G27)/BalanceSheet!G30 -> 0.39997585 | H10: =(BalanceSheet!H18+BalanceSheet!H27)/BalanceSheet!H30 -> 0.38489944 | I10: =(BalanceSheet!I18+BalanceSheet!I27)/BalanceSheet!I30 -> 0.3712306
A11: Interst Coverage | B11: =IncomeStatement!B18/IncomeStatement!B19 -> 14.066667 | C11: =IncomeStatement!C18/IncomeStatement!C19 -> 22.785714 | D11: =IncomeStatement!D18/IncomeStatement!D19 -> 13.87931 | E11: =IncomeStatement!E18/IncomeStatement!E19 -> 14.328156 | F11: =IncomeStatement!F18/IncomeStatement!F19 -> 14.770299 | G11: =IncomeStatement!G18/IncomeStatement!G19 -> 15.2046 | H11: =IncomeStatement!H18/IncomeStatement!H19 -> 15.630008 | I11: =IncomeStatement!I18/IncomeStatement!I19 -> 16.045563
A12: Efficiency Ratios:
A13: Asset turnover | B13: =IncomeStatement!B7/BalanceSheet!B15 -> 0.91296863 | C13: =IncomeStatement!C7/BalanceSheet!C15 -> 0.87583389 | D13: =IncomeStatement!D7/BalanceSheet!D15 -> 0.80649578 | E13: =IncomeStatement!E7/BalanceSheet!E15 -> 0.80649578 | F13: =IncomeStatement!F7/BalanceSheet!F15 -> 0.80649578 | G13: =IncomeStatement!G7/BalanceSheet!G15 -> 0.80649578 | H13: =IncomeStatement!H7/BalanceSheet!H15 -> 0.80649578 | I13: =IncomeStatement!I7/BalanceSheet!I15 -> 0.80649578
A14: Inventory turnover | B14: =(IncomeStatement!B10+IncomeStatement!B11+IncomeStatement!B12)/BalanceSheet!B7 -> 14.268102 | C14: =(IncomeStatement!C10+IncomeStatement!C11+IncomeStatement!C12)/BalanceSheet!C7 -> 14.834879 | D14: =(IncomeStatement!D10+IncomeStatement!D11+IncomeStatement!D12)/BalanceSheet!D7 -> 13.025641 | E14: =(IncomeStatement!E10+IncomeStatement!E11+IncomeStatement!E12)/BalanceSheet!E7 -> 13.025641 | F14: =(IncomeStatement!F10+IncomeStatement!F11+IncomeStatement!F12)/BalanceSheet!F7 -> 13.025641 | G14: =(IncomeStatement!G10+IncomeStatement!G11+IncomeStatement!G12)/BalanceSheet!G7 -> 13.025641 | H14: =(IncomeStatement!H10+IncomeStatement!H11+IncomeStatement!H12)/BalanceSheet!H7 -> 13.025641 | I14: =(IncomeStatement!I10+IncomeStatement!I11+IncomeStatement!I12)/BalanceSheet!I7 -> 13.025641
A15: Receivable turnover | B15: =(BalanceSheet!B5+BalanceSheet!B6)/(IncomeStatement!B7/360) -> 60.377121 | C15: =(BalanceSheet!C5+BalanceSheet!C6)/(IncomeStatement!C7/360) -> 61.319623 | D15: =(BalanceSheet!D5+BalanceSheet!D6)/(IncomeStatement!D7/360) -> 60.537584 | E15: =(BalanceSheet!E5+BalanceSheet!E6)/(IncomeStatement!E7/360) -> 60.537584 | F15: =(BalanceSheet!F5+BalanceSheet!F6)/(IncomeStatement!F7/360) -> 60.537584 | G15: =(BalanceSheet!G5+BalanceSheet!G6)/(IncomeStatement!G7/360) -> 60.537584 | H15: =(BalanceSheet!H5+BalanceSheet!H6)/(IncomeStatement!H7/360) -> 60.537584 | I15: =(BalanceSheet!I5+BalanceSheet!I6)/(IncomeStatement!I7/360) -> 60.537584

Sheet Sheet5
